README.md
setup.cfg
setup.py
aerolyzer/__init__.py
aerolyzer/aerosol.py
aerolyzer/image_restriction_functions.py
aerolyzer/image_restriction_main.py
aerolyzer/location.py
aerolyzer/retrieve_image_data.py
aerolyzer/test_aerosol.py
aerolyzer/test_location.py
aerolyzer/test_wavelength.py
aerolyzer/wavelength.py
aerolyzer/wunderData.py
aerolyzer.egg-info/PKG-INFO
aerolyzer.egg-info/SOURCES.txt
aerolyzer.egg-info/dependency_links.txt
aerolyzer.egg-info/namespace_packages.txt
aerolyzer.egg-info/not-zip-safe
aerolyzer.egg-info/requires.txt
aerolyzer.egg-info/top_level.txt