Metadata-Version: 1.1
Name: aerolyzer
Version: 0.0.0.9
Summary: Aerolyzer analyzes images to infer atmospheric composition
Home-page: https://github.com/Aerolyzer/Aerolyzer
Author: Aerolyzer Developers
Author-email: aerolyzer@googlegroups.com
License: Apache License, Version 2.0
Download-URL: https://github.com/Aerolyzer/Aerolyzer/archive/0.0.0.9.tar.gz
Keywords: atmospheric composition,sunsets,image analysis,aerosols
Platform: UNKNOWN
Classifier: Environment :: Console
Classifier: Intended Audience :: Developers
Classifier: Intended Audience :: Information Technology
Classifier: Intended Audience :: Science/Research
Classifier: Topic :: Scientific/Engineering
Classifier: Development Status :: 1 - Planning
Classifier: License :: OSI Approved :: Apache Software License
Classifier: Operating System :: OS Independent
Classifier: Programming Language :: Python
Classifier: Topic :: Software Development :: Libraries :: Python Modules
